framedork/__init__.py
framedork/framedork.py
framedork/src/__init__.py
framedork/src/DORM/__init__.py
framedork/src/DORM/dorm.py
framedork/src/etc/__init__.py
framedork/src/etc/settings.py
framedork/src/etc/wsgi.py
framedork/src/exceptions/__init__.py
framedork/src/exceptions/handler_exceptions.py
framedork/src/handlers/__init__.py
framedork/src/handlers/handlers.py
framedork/src/preprocessors/HTML.py
framedork/src/preprocessors/Request.py
framedork/src/preprocessors/Response.py
framedork/src/preprocessors/__init__.py
framedork.py-0.1.0.dist-info/METADATA
framedork.py-0.1.0.dist-info/WHEEL
framedork.py-0.1.0.dist-info/top_level.txt
framedork.py-0.1.0.dist-info/RECORD
