Metadata-Version: 2.1
Name: framedork.py
Version: 0.1.0
Summary: A meme web framework on Python
Home-page: https://github.com/RedmanPlus/framedork.py
Download-URL: https://github.com/RedmanPlus/framedork.py/tarball/v0.1.0
Author: Antony Redman
Author-email: RumataYounger@gmail.com
License: MIT
Keywords: web,wsgi,framework
